trafficlight/trafficlight.v
module traffic_light (
    input clk,
    input rst,
    output reg [2:0] light_NS, // [Red, Yellow, Green]
    output reg [2:0] light_EW  // [Red, Yellow, Green]
);

    // State Encoding
    parameter S0 = 2'b00, // NS Green, EW Red
              S1 = 2'b01, // NS Yellow, EW Red
              S2 = 2'b10, // NS Red, EW Green
              S3 = 2'b11; // NS Red, EW Yellow

    reg [1:0] current_state, next_state;
    reg [3:0] count; // Timer to keep track of clock cycles

    // State Transition Logic (Sequential)
    always @(posedge clk or posedge rst) begin
        if (rst) begin
            current_state <= S0;
            count <= 0;
        end else begin
            if (count == 4'd10) begin // Change state every 10 clock cycles
                current_state <= next_state;
                count <= 0;
            end else begin
                count <= count + 1;
            end
        end
    end

    // Next State Logic (Combinational)
    always @(*) begin
        case (current_state)
            S0: next_state = S1;
            S1: next_state = S2;
            S2: next_state = S3;
            S3: next_state = S0;
            default: next_state = S0;
        endcase
    end

    // Output Logic (Combinational)
    always @(*) begin
        case (current_state)
            S0: begin light_NS = 3'b001; light_EW = 3'b100; end // NS Green, EW Red
            S1: begin light_NS = 3'b010; light_EW = 3'b100; end // NS Yellow, EW Red
            S2: begin light_NS = 3'b100; light_EW = 3'b001; end // NS Red, EW Green
            S3: begin light_NS = 3'b100; light_EW = 3'b010; end // NS Red, EW Yellow
            default: begin light_NS = 3'b100; light_EW = 3'b100; end
        endcase
    end

endmodule

trafficlight/testbench_trafficlight.v
`timescale 1ns / 1ps

module traffic_light_tb;
    reg clk;
    reg rst;
    wire [2:0] light_NS;
    wire [2:0] light_EW;

    // Instantiate the traffic light controller
    traffic_light uut (
        .clk(clk),
        .rst(rst),
        .light_NS(light_NS),
        .light_EW(light_EW)
    );

    // Generate Clock (toggles every 5ns, creating a 10ns period)
    always #5 clk = ~clk;

    initial begin
        // Setup file dumping for GTKWave
        $dumpfile("traffic_light_simulation.vcd");
        $dumpvars(0, traffic_light_tb);

        // Initialize Inputs
        clk = 0;
        rst = 1;
        #20; // Hold reset for 20ns
        
        rst = 0; // Release reset
        #500;    // Run simulation for 500ns
        
        $finish; // End simulation
    end
endmodule

traffic_light_simulation.vcd
$date
	Sun Jun  7 10:49:07 2026
$end
$version
	Icarus Verilog
$end
$timescale
	1ps
$end
$scope module traffic_light_tb $end
$var wire 3 ! light_NS [2:0] $end
$var wire 3 " light_EW [2:0] $end
$var reg 1 # clk $end
$var reg 1 $ rst $end
$scope module uut $end
$var wire 1 # clk $end
$var wire 1 $ rst $end
$var parameter 2 % S0 $end
$var parameter 2 & S1 $end
$var parameter 2 ' S2 $end
$var parameter 2 ( S3 $end
$var reg 4 ) count [3:0] $end
$var reg 2 * current_state [1:0] $end
$var reg 3 + light_EW [2:0] $end
$var reg 3 , light_NS [2:0] $end
$var reg 2 - next_state [1:0] $end
$upscope $end
$upscope $end
$enddefinitions $end
$comment Show the parameter values. $end
$dumpall
b11 (
b10 '
b1 &
b0 %
$end
#0
$dumpvars
b1 -
b1 ,
b100 +
b0 *
b0 )
1$
0#
b100 "
b1 !
$end
#5000
1#
#10000
0#
#15000
1#
#20000
0#
0$
#25000
b1 )
1#
#30000
0#
#35000
b10 )
1#
#40000
0#
#45000
b11 )
1#
#50000
0#
#55000
b100 )
1#
#60000
0#
#65000
b101 )
1#
#70000
0#
#75000
b110 )
1#
#80000
0#
#85000
b111 )
1#
#90000
0#
#95000
b1000 )
1#
#100000
0#
#105000
b1001 )
1#
#110000
0#
#115000
b1010 )
1#
#120000
0#
#125000
b10 -
b10 !
b10 ,
b0 )
b1 *
1#
#130000
0#
#135000
b1 )
1#
#140000
0#
#145000
b10 )
1#
#150000
0#
#155000
b11 )
1#
#160000
0#
#165000
b100 )
1#
#170000
0#
#175000
b101 )
1#
#180000
0#
#185000
b110 )
1#
#190000
0#
#195000
b111 )
1#
#200000
0#
#205000
b1000 )
1#
#210000
0#
#215000
b1001 )
1#
#220000
0#
#225000
b1010 )
1#
#230000
0#
#235000
b1 "
b1 +
b100 !
b100 ,
b11 -
b0 )
b10 *
1#
#240000
0#
#245000
b1 )
1#
#250000
0#
#255000
b10 )
1#
#260000
0#
#265000
b11 )
1#
#270000
0#
#275000
b100 )
1#
#280000
0#
#285000
b101 )
1#
#290000
0#
#295000
b110 )
1#
#300000
0#
#305000
b111 )
1#
#310000
0#
#315000
b1000 )
1#
#320000
0#
#325000
b1001 )
1#
#330000
0#
#335000
b1010 )
1#
#340000
0#
#345000
b0 -
b10 "
b10 +
b0 )
b11 *
1#
#350000
0#
#355000
b1 )
1#
#360000
0#
#365000
b10 )
1#
#370000
0#
#375000
b11 )
1#
#380000
0#
#385000
b100 )
1#
#390000
0#
#395000
b101 )
1#
#400000
0#
#405000
b110 )
1#
#410000
0#
#415000
b111 )
1#
#420000
0#
#425000
b1000 )
1#
#430000
0#
#435000
b1001 )
1#
#440000
0#
#445000
b1010 )
1#
#450000
0#
#455000
b100 "
b100 +
b1 !
b1 ,
b1 -
b0 )
b0 *
1#
#460000
0#
#465000
b1 )
1#
#470000
0#
#475000
b10 )
1#
#480000
0#
#485000
b11 )
1#
#490000
0#
#495000
b100 )
1#
#500000
0#
#505000
b101 )
1#
#510000
0#
#515000
b110 )
1#
